belief/__init__.py
belief-0.0.2.dist-info/LICENSE
belief-0.0.2.dist-info/METADATA
belief-0.0.2.dist-info/WHEEL
belief-0.0.2.dist-info/top_level.txt
belief-0.0.2.dist-info/RECORD
